mypackagess/__init__.py
mypackagess/sample.py
mypackagess/app/MyTest.py
mypackagess/app/__init__.py
mypackagess/app/logers.py
mypackagess/app/main.py
mypackagess/app/mqtt_con.py
mypackagess/app/rpm.py
mypackagess/app/util.py
mypackagess/app/util2.py
mypackagess/app/vanalytics_api.py
mypackagess/app/vanalytics_data.py
mypackagess/app/vanalytics_data1.py
mypackagess/app/vanalytics_helper.py
mypackagess/app/vmaint_constants.py
mypackagess/app/bearing/__init__.py
mypackagess/app/bearing/bearing.py
mypackagess/app/gear/__init__.py
mypackagess/app/gear/gear.py
mypackagess/app/looseness/__init__.py
mypackagess/app/looseness/looseness.py
mypackagess/app/looseness/looseness_v1.py
mypackagess/app/looseness/los_2_new.py
mypackagess/app/machine_status/__init__.py
mypackagess/app/machine_status/on_off.py
mypackagess/app/machine_status/onof_three_axis_average.py
mypackagess/app/misalignment/__init__.py
mypackagess/app/misalignment/misalignment.py
mypackagess/app/misalignment/misalignment_new_version.py
mypackagess/app/misalignment/misalignment_v1.py
mypackagess/app/phase/__init__.py
mypackagess/app/phase/phase_angle.py
mypackagess/app/unbalance/__init__.py
mypackagess/app/unbalance/ub1.py
mypackagess/app/unbalance/unbalance.py
mypackagess/app/unbalance/unbalance_v1.py
mypackagess/app/velocity_severity/__init__.py
mypackagess/app/velocity_severity/machine_condition.py
mypackagess-0.0.1.dist-info/METADATA
mypackagess-0.0.1.dist-info/WHEEL
mypackagess-0.0.1.dist-info/top_level.txt
mypackagess-0.0.1.dist-info/RECORD
