Metadata-Version: 2.1
Name: mypackagess
Version: 0.0.1
Summary: My first Python package
Author: Supriya
Author-email: <supriyasuhas058@email.com>
Keywords: python,first package
